pierwszatv/__init__.py
pierwszatv/models.py
pierwszatv/providers.py
pierwszatv/urls.py
pierwszatv/api/__init__.py
pierwszatv/api/clients.py
pierwszatv/api/exceptions.py
pierwszatv/api/models.py
pierwszatv/api/providers.py
pierwszatv/socket/__init__.py
pierwszatv/socket/clients.py
pierwszatv/socket/exceptions.py
pierwszatv/socket/models.py
pierwszatv/socket/providers.py
pierwszatv-0.0.1.dist-info/DESCRIPTION.rst
pierwszatv-0.0.1.dist-info/METADATA
pierwszatv-0.0.1.dist-info/metadata.json
pierwszatv-0.0.1.dist-info/RECORD
pierwszatv-0.0.1.dist-info/top_level.txt
pierwszatv-0.0.1.dist-info/WHEEL
