Metadata-Version: 2.0
Name: pierwszatv
Version: 0.0.1
Summary: UNKNOWN
Home-page: https://github.com/p1c2u/pierwszatv
Author: Artur Maciąg
Author-email: maciag.artur@gmail.com
License: UNKNOWN
Platform: UNKNOWN
Classifier: Intended Audience :: Developers
Classifier: Programming Language :: Python :: 3.4
Classifier: Programming Language :: Python :: 3.5
Classifier: Topic :: Software Development :: Libraries
Requires-Dist: requests
Requires-Dist: six
Requires-Dist: socketIO-client
